setup.py
easythread/__init__.py
easythread/custom_exception.py
easythread/multi_thread.py
easythread/utils.py
easythread.egg-info/PKG-INFO
easythread.egg-info/SOURCES.txt
easythread.egg-info/dependency_links.txt
easythread.egg-info/top_level.txt