Metadata-Version: 1.0
Name: easythread
Version: 0.2
Summary: multi thread tool
Home-page: https://www.google.com/
Author: Hcyangnull
Author-email: hcyang@gmail.com
License: UNKNOWN
Platform: UNKNOWN
